Perkiraan_Cuaca/__init__.py
Perkiraan_cuaca_temanggung-1.0.dist-info/LICENSE
Perkiraan_cuaca_temanggung-1.0.dist-info/METADATA
Perkiraan_cuaca_temanggung-1.0.dist-info/WHEEL
Perkiraan_cuaca_temanggung-1.0.dist-info/top_level.txt
Perkiraan_cuaca_temanggung-1.0.dist-info/RECORD
